README.md
setup.py
colour_printing/__init__.py
colour_printing/cmdline.py
colour_printing/exception.py
colour_printing/helper.py
colour_printing/small_tool.py
colour_printing/style.py
colour_printing.egg-info/PKG-INFO
colour_printing.egg-info/SOURCES.txt
colour_printing.egg-info/dependency_links.txt
colour_printing.egg-info/entry_points.txt
colour_printing.egg-info/top_level.txt
colour_printing/config/__init__.py
colour_printing/config/config.py
colour_printing/custom/__init__.py
colour_printing/custom/printme.py
colour_printing/default/__init__.py
colour_printing/default/default_colour_printing_config.py
colour_printing/default/default_log.py