Metadata-Version: 1.1
Name: colour-printing
Version: 0.3.23
Summary: colour-printing
Home-page: https://github.com/Faithforus/Colour-printing
Author: faithforus
Author-email: ljunf817@163.com
License: MIT
Keywords: python package print
Platform: UNKNOWN
Classifier: Programming Language :: Python :: 3
Classifier: License :: OSI Approved :: MIT License
Classifier: Operating System :: OS Independent
